pyramid_bugsnag/__init__.py
pyramid_bugsnag/tween.py
pyramid_bugsnag-0.4.dist-info/DESCRIPTION.rst
pyramid_bugsnag-0.4.dist-info/LICENSE.txt
pyramid_bugsnag-0.4.dist-info/METADATA
pyramid_bugsnag-0.4.dist-info/RECORD
pyramid_bugsnag-0.4.dist-info/WHEEL
pyramid_bugsnag-0.4.dist-info/metadata.json
pyramid_bugsnag-0.4.dist-info/top_level.txt
