Metadata-Version: 2.0
Name: pyramid-bugsnag
Version: 0.4
Summary: Pyramid extension to send exceptions to Bugsnag
Home-page: https://github.com/pior/pyramid_bugsnag
Author: Pior Bastida
Author-email: pior@pbastida.net
License: MIT
Keywords: wsgi pylons pyramid bugsnag tween exception handler
Platform: UNKNOWN
Classifier: Intended Audience :: Developers
Classifier: Programming Language :: Python
Classifier: Programming Language :: Python :: 2
Classifier: Programming Language :: Python :: 2.7
Classifier: Programming Language :: Python :: 3
Classifier: Programming Language :: Python :: 3.4
Classifier: Programming Language :: Python :: 3.5
Classifier: Programming Language :: Python :: 3.6
Classifier: Programming Language :: Python :: Implementation :: PyPy
Classifier: Framework :: Pyramid
Classifier: License :: OSI Approved :: MIT License
Requires-Dist: pyramid (>=1.5)
Requires-Dist: bugsnag
